steamcrawl/__init__.py
steamcrawl/exceptions.py
steamcrawl/request.py
steamcrawl-1.0.0.dist-info/LICENSE
steamcrawl-1.0.0.dist-info/METADATA
steamcrawl-1.0.0.dist-info/WHEEL
steamcrawl-1.0.0.dist-info/top_level.txt
steamcrawl-1.0.0.dist-info/RECORD
