Metadata-Version: 2.1
Name: steamcrawl
Version: 1.0.0
Summary: A package that helps extract Steam store and community market data as pandas DataFrame for better readabilty and usability.
Home-page: https://github.com/Hungreeee/steamcrawl
Author: Hungreeee
Author-email: hungmnguyen13102003@gmail.com
License: MIT
Platform: UNKNOWN
License-File: LICENSE
Requires-Dist: requests
Requires-Dist: pandas
Requires-Dist: selenium-wire
